[
    {
        "price": 125,
        "quantity": 5,
        "portfolio_id": 1,
        "symbol_id": 1
    },
    {
        "price": 180,
        "quantity": 8,
        "portfolio_id": 1,
        "symbol_id": 1
    },
    {
        "price": 700,
        "quantity": 10,
        "portfolio_id": 2,
        "symbol_id": 1
    },
    {
        "price": 40,
        "quantity": 100,
        "portfolio_id": 2,
        "symbol_id": 2
    },
    {
        "price": 75,
        "quantity": 10,
        "portfolio_id": 2,
        "symbol_id": 3
    }
]